certbot_dns_transip/__init__.py
certbot_dns_transip/dns_transip.py
certbot_dns_transip/dns_transip_test.py
certbot_dns_transip_simple-1.2.0.dist-info/LICENSE.txt
certbot_dns_transip_simple-1.2.0.dist-info/METADATA
certbot_dns_transip_simple-1.2.0.dist-info/WHEEL
certbot_dns_transip_simple-1.2.0.dist-info/entry_points.txt
certbot_dns_transip_simple-1.2.0.dist-info/top_level.txt
certbot_dns_transip_simple-1.2.0.dist-info/RECORD
