Metadata-Version: 2.1
Name: certbot-dns-transip-simple
Version: 1.2.0
Summary: transip DNS Authenticator plugin for Certbot, simple to set up, no docker etc.
Home-page: https://gitea.caret.be/jens/certbot-dns-transip
Author: Jens Timmerman
Author-email: certbotdnstransip@caret.be
License: Apache License 2.0
Classifier: Development Status :: 3 - Alpha
Classifier: Environment :: Plugins
Classifier: Intended Audience :: System Administrators
Classifier: License :: OSI Approved :: Apache Software License
Classifier: Operating System :: POSIX :: Linux
Classifier: Programming Language :: Python
Classifier: Programming Language :: Python :: 2
Classifier: Programming Language :: Python :: 2.7
Classifier: Programming Language :: Python :: 3
Classifier: Programming Language :: Python :: 3.4
Classifier: Programming Language :: Python :: 3.5
Classifier: Programming Language :: Python :: 3.6
Classifier: Programming Language :: Python :: 3.7
Classifier: Topic :: Internet :: WWW/HTTP
Classifier: Topic :: Security
Classifier: Topic :: System :: Installation/Setup
Classifier: Topic :: System :: Networking
Classifier: Topic :: System :: Systems Administration
Classifier: Topic :: Utilities
Requires-Python: >=2.7, !=3.0.*, !=3.1.*, !=3.2.*, !=3.3.*
License-File: LICENSE.txt
Requires-Dist: acme >=0.29.0
Requires-Dist: certbot >=0.34.0
Requires-Dist: setuptools
Requires-Dist: zope
Requires-Dist: mock
Requires-Dist: python-transip
